{
  "version": "7",
  "dialect": "postgresql",
  "entries": [
    {
      "idx": 0,
      "version": "7",
      "when": 1765577249035,
      "tag": "0000_black_pretty_boy",
      "breakpoints": true
    },
    {
      "idx": 1,
      "version": "7",
      "when": 1765675924293,
      "tag": "0001_smiling_mysterio",
      "breakpoints": true
    },
    {
      "idx": 2,
      "version": "7",
      "when": 1765766022721,
      "tag": "0002_overrated_blindfold",
      "breakpoints": true
    },
    {
      "idx": 3,
      "version": "7",
      "when": 1765781547869,
      "tag": "0003_confused_doctor_spectrum",
      "breakpoints": true
    },
    {
      "idx": 4,
      "version": "7",
      "when": 1765802324447,
      "tag": "0004_normal_lake",
      "breakpoints": true
    }
  ]
}